sweatstack/__init__.py
sweatstack/cli.py
sweatstack/client.py
sweatstack/constants.py
sweatstack/ipython_init.py
sweatstack/jupyterlab_oauth2_startup.py
sweatstack/openapi_schemas.py
sweatstack/py.typed
sweatstack/schemas.py
sweatstack/streamlit.py
sweatstack/sweatshell.py
sweatstack/utils.py
sweatstack/Sweat Stack examples/Getting started.ipynb
sweatstack/fastapi/__init__.py
sweatstack/fastapi/config.py
sweatstack/fastapi/dependencies.py
sweatstack/fastapi/models.py
sweatstack/fastapi/routes.py
sweatstack/fastapi/session.py
sweatstack-0.61.0.dist-info/METADATA
sweatstack-0.61.0.dist-info/WHEEL
sweatstack-0.61.0.dist-info/entry_points.txt
sweatstack-0.61.0.dist-info/RECORD
